simple_injection/__init__.py
simple_injection/service_collection.py
tests/__init__.py
tests/classes.py
tests/test_auto_resolve.py
tests/test_exceptions.py
tests/test_instance.py
tests/test_optional.py
tests/test_run_function.py
tests/test_singleton.py
tests/test_transient.py
simple_injection-0.2.5.dist-info/LICENSE
simple_injection-0.2.5.dist-info/METADATA
simple_injection-0.2.5.dist-info/WHEEL
simple_injection-0.2.5.dist-info/top_level.txt
simple_injection-0.2.5.dist-info/RECORD
