Metadata-Version: 2.1
Name: simple-injection
Version: 0.2.5
Summary: A simple library for typing-based dependency injection
Home-page: https://github.com/BradLewis/simple-injection
Author: Bradley Lewis
License: MIT
Platform: UNKNOWN
Classifier: Programming Language :: Python :: 3
Classifier: License :: OSI Approved :: MIT License
Classifier: Operating System :: OS Independent
Requires-Python: >=3.5
License-File: LICENSE
